setup.cfg
setup.py
slackmojify/__init__.py
slackmojify/images2gif.py
slackmojify/slackmojify.py
slackmojify.egg-info/PKG-INFO
slackmojify.egg-info/SOURCES.txt
slackmojify.egg-info/dependency_links.txt
slackmojify.egg-info/entry_points.txt
slackmojify.egg-info/not-zip-safe
slackmojify.egg-info/requires.txt
slackmojify.egg-info/top_level.txt