Metadata-Version: 1.1
Name: slackmojify
Version: 0.1.1
Summary: Create emojis so that they can be uploaded to Slack.
Home-page: https://github.com/sgp715/slackmojify
Author: Sebastian Perez
Author-email: 7sebastianperez@gmail.com
License: MIT
Keywords: slack,emoji
Platform: UNKNOWN
Classifier: Development Status :: 3 - Alpha
Classifier: Programming Language :: Python :: 3.5
